gitlabenvmngr/__init__.py
gitlabenvmngr/__main__.py
gitlabenvmngr/api.py
gitlabenvmngr/helps.py
gitlabenvmngr/screens.py
gitlabenvmngr-0.2.1.dist-info/METADATA
gitlabenvmngr-0.2.1.dist-info/WHEEL
gitlabenvmngr-0.2.1.dist-info/entry_points.txt
gitlabenvmngr-0.2.1.dist-info/top_level.txt
gitlabenvmngr-0.2.1.dist-info/RECORD
