Metadata-Version: 2.1
Name: gitlabenvmngr
Version: 0.2.1
Summary: Package to manage Gitlab environment variables
Home-page: https://gitlab.com
Author: Alejandro Pinar Ruiz
Author-email: alejandropinarruiz@gmail.com
License: UNKNOWN
Platform: UNKNOWN
Classifier: Programming Language :: Python :: 3
Classifier: License :: OSI Approved :: MIT License
Classifier: Operating System :: OS Independent
Requires-Dist: argparse
Requires-Dist: requests
Requires-Dist: PyInquirer
Requires-Dist: rich
